pyemits/__init__.py
pyemits/common/__init__.py
pyemits/common/config_model.py
pyemits/common/data_model.py
pyemits/common/errors.py
pyemits/common/io/__init__.py
pyemits/common/io/db.py
pyemits/common/io/local.py
pyemits/common/py_native_dtype.py
pyemits/common/stats.py
pyemits/common/typing/__init__.py
pyemits/common/typing/data_format.py
pyemits/common/utils/__init__.py
pyemits/common/utils/json_utils.py
pyemits/common/utils/misc_utils.py
pyemits/common/utils/proxy.py
pyemits/common/validation.py
pyemits/core/__init__.py
pyemits/core/evaluation/__init__.py
pyemits/core/evaluation/backtesting.py
pyemits/core/evaluation/data_profile.py
pyemits/core/evaluation/model_evaluation.py
pyemits/core/ml/__init__.py
pyemits/core/ml/anomaly_detection/__init__.py
pyemits/core/ml/anomaly_detection/predictor.py
pyemits/core/ml/anomaly_detection/trainer.py
pyemits/core/ml/base.py
pyemits/core/ml/cross_validation.py
pyemits/core/ml/regression/__init__.py
pyemits/core/ml/regression/ensemble.py
pyemits/core/ml/regression/nn.py
pyemits/core/ml/regression/predictor.py
pyemits/core/ml/regression/trainer.py
pyemits/core/preprocessing/__init__.py
pyemits/core/preprocessing/aggregation.py
pyemits/core/preprocessing/cleansing.py
pyemits/core/preprocessing/dimensional_reduction.py
pyemits/core/preprocessing/misc_utils.py
pyemits/core/preprocessing/pipeline.py
pyemits/core/preprocessing/scaling.py
pyemits/core/preprocessing/splitting.py
pyemits/services/__init__.py
pyemits-0.1.2.0.dist-info/LICENSE
pyemits-0.1.2.0.dist-info/WHEEL
pyemits-0.1.2.0.dist-info/METADATA
pyemits-0.1.2.0.dist-info/RECORD
