Metadata-Version: 2.1
Name: pyemits
Version: 0.1.2.0
Summary: python package for easy manipulation on time series data for quick insight
Home-page: https://github.com/thompson0012/PyEmits
License: Apache-2.0
Keywords: data-science,python,machine-learning,pyemits,framework
Author: thompson0012
Author-email: 51963680+thompson0012@users.noreply.github.com
Requires-Python: >=3.8.3,<3.10
Classifier: License :: OSI Approved :: Apache Software License
Classifier: Programming Language :: Python :: 3
Classifier: Programming Language :: Python :: 3.9
Classifier: Topic :: Scientific/Engineering :: Artificial Intelligence
Classifier: Topic :: Software Development :: Libraries :: Python Modules
Requires-Dist: SQLAlchemy (>=1.4.29,<2.0.0)
Requires-Dist: arrow (>=1.2.0,<2.0.0)
Requires-Dist: combo (>=0.1.2,<0.2.0)
Requires-Dist: dask (>=2021.9.1,<2022.0.0)
Requires-Dist: filterpy (>=1.4.5,<2.0.0)
Requires-Dist: jax (>=0.2.24,<0.3.0)
Requires-Dist: jaxlib (>=0.1.73,<0.2.0)
Requires-Dist: joblib (>=1.1.0,<2.0.0)
Requires-Dist: keras (>=2.6.0,<3.0.0)
Requires-Dist: lightgbm (>=3.3.0,<4.0.0)
Requires-Dist: modin (>=0.11.1,<0.12.0)
Requires-Dist: pyarrow (>=5.0.0,<6.0.0)
Requires-Dist: pydantic (>=1.8.2,<2.0.0)
Requires-Dist: pykalman (>=0.9.5,<0.10.0)
Requires-Dist: pyod (>=0.9.4,<0.10.0)
Requires-Dist: pytorch-lightning (>=1.4.9,<2.0.0)
Requires-Dist: ray (>=1.7.0,<2.0.0)
Requires-Dist: scikit-learn (>=1.0,<2.0)
Requires-Dist: sqlmodel (>=0.0.6,<0.0.7)
Requires-Dist: statsmodels (>=0.13.0,<0.14.0)
Requires-Dist: suod (>=0.0.8,<0.0.9)
Requires-Dist: tensorflow (>=2.6.0,<3.0.0)
Requires-Dist: xgboost (>=1.5.0,<2.0.0)
Project-URL: Repository, https://github.com/thompson0012/PyEmits
